generalize_config/__init__.py
generalize_config/generalize.py
generalize_config/read_config.py
generalize_config/inspect/__init__.py
generalize_config/inspect/member.py
generalize_config/namespace/__init__.py
generalize_config/namespace/merge.py
generalize_config/namespace/strip.py
generalize_config/namespace/types.py
generalize_config/parser/__init__.py
generalize_config/parser/cfg_parse.py
generalize_config/parser/dict_parse.py
generalize_config/parser/env_parse.py
generalize_config/parser/json_parse.py
generalize_config/parser/yaml_parse.py
generalize_config-1.3.0.dist-info/LICENSE
generalize_config-1.3.0.dist-info/METADATA
generalize_config-1.3.0.dist-info/WHEEL
generalize_config-1.3.0.dist-info/top_level.txt
generalize_config-1.3.0.dist-info/RECORD
